{
  "project_info": {
    "project_number": "599611363804",
    "project_id": "incognito-staging",
    "storage_bucket": "incognito-staging.appspot.com"
  },
  "client": [
    {
      "client_info": {
        "mobilesdk_app_id": "1:599611363804:android:a026e15d8637411a677f19",
        "android_client_info": {
          "package_name": "com.incognito.mobilewallet"
        }
      },
      "oauth_client": [],
      "api_key": [
        {
          "current_key": "AIzaSyCv64ZlfeEINZHvFuxPa0ry8bz_rEoK-lE"
        }
      ],
      "services": {
        "appinvite_service": {
          "other_platform_oauth_client": []
        }
      }
    },
    {
      "client_info": {
        "mobilesdk_app_id": "1:599611363804:android:a026e15d8637411a677f19",
        "android_client_info": {
          "package_name": "com.incognito.mobilewallet.debug"
        }
      },
      "oauth_client": [],
      "api_key": [
        {
          "current_key": "AIzaSyCv64ZlfeEINZHvFuxPa0ry8bz_rEoK-lE"
        }
      ],
      "services": {
        "appinvite_service": {
          "other_platform_oauth_client": []
        }
      }
    },
    {
      "client_info": {
        "mobilesdk_app_id": "1:599611363804:android:a026e15d8637411a677f19",
        "android_client_info": {
          "package_name": "com.incognito.mobilewallet.staging"
        }
      },
      "oauth_client": [],
      "api_key": [
        {
          "current_key": "AIzaSyCv64ZlfeEINZHvFuxPa0ry8bz_rEoK-lE"
        }
      ],
      "services": {
        "appinvite_service": {
          "other_platform_oauth_client": []
        }
      }
    },
    {
      "client_info": {
        "mobilesdk_app_id": "1:599611363804:android:a026e15d8637411a677f19",
        "android_client_info": {
          "package_name": "com.incognito.mobilewallet.next"
        }
      },
      "oauth_client": [],
      "api_key": [
        {
          "current_key": "AIzaSyCv64ZlfeEINZHvFuxPa0ry8bz_rEoK-lE"
        }
      ],
      "services": {
        "appinvite_service": {
          "other_platform_oauth_client": []
        }
      }
    },
    {
      "client_info": {
        "mobilesdk_app_id": "1:599611363804:android:a026e15d8637411a677f19",
        "android_client_info": {
          "package_name": "com.incognito.mobilewallet.next2"
        }
      },
      "oauth_client": [],
      "api_key": [
        {
          "current_key": "AIzaSyCv64ZlfeEINZHvFuxPa0ry8bz_rEoK-lE"
        }
      ],
      "services": {
        "appinvite_service": {
          "other_platform_oauth_client": []
        }
      }
    },
    {
      "client_info": {
        "mobilesdk_app_id": "1:599611363804:android:a026e15d8637411a677f19",
        "android_client_info": {
          "package_name": "com.incognito.mobilewallet.next3"
        }
      },
      "oauth_client": [],
      "api_key": [
        {
          "current_key": "AIzaSyCv64ZlfeEINZHvFuxPa0ry8bz_rEoK-lE"
        }
      ],
      "services": {
        "appinvite_service": {
          "other_platform_oauth_client": []
        }
      }
    }
  ],
  "configuration_version": "1"
}
